ica_aroma_py/__init__.py
ica_aroma_py/__main__.py
ica_aroma_py/resources/mask_csf.nii.gz
ica_aroma_py/resources/mask_edge.nii.gz
ica_aroma_py/resources/mask_out.nii.gz
ica_aroma_py/services/ICA_AROMA_functions.py
ica_aroma_py/services/ICA_AROMA_nodes.py
ica_aroma_py/services/__init__.py
ica_aroma_py/services/classification_plots.py
ica_aroma_py/services/cli.py
ica_aroma_py/services/pipeline.py
ica_aroma_py/services/workflow.py
ica_aroma_py-0.1.2.dist-info/licenses/license.md
ica_aroma_py-0.1.2.dist-info/METADATA
ica_aroma_py-0.1.2.dist-info/WHEEL
ica_aroma_py-0.1.2.dist-info/entry_points.txt
ica_aroma_py-0.1.2.dist-info/top_level.txt
ica_aroma_py-0.1.2.dist-info/RECORD
