Metadata-Version: 2.4
Name: ica-aroma-py
Version: 0.1.2
Summary: ICA-AROMA packaged for Python import usage.
Home-page: https://github.com/LICE-dev/ICA-AROMA-PY
License: Apache-2.0
Requires-Python: >=3.10
License-File: license.md
Requires-Dist: numpy==2.2.4
Requires-Dist: nibabel<6,>=5.3.0
Provides-Extra: nipype
Requires-Dist: nipype==1.10.0; extra == "nipype"
Provides-Extra: plots
Requires-Dist: pandas; extra == "plots"
Requires-Dist: matplotlib==3.10.1; extra == "plots"
Requires-Dist: seaborn<0.14,>=0.13.2; extra == "plots"
Dynamic: home-page
Dynamic: license
Dynamic: license-file
Dynamic: provides-extra
Dynamic: requires-dist
Dynamic: requires-python
Dynamic: summary
